[
    {
        "user": "<@291788732544057355>",
        "timestamp": "2023 Oct, 13",
        "lore": "this is a test"
    },
    {
        "user": "<@291788732544057355>",
        "user_tag": "fz",
        "timestamp": "2023 Oct, 13",
        "lore": "brian is the hottest dude at the peak"
    },
    {
        "user": "<@291788732544057355>",
        "user_tag": "fz",
        "timestamp": "2023 Oct, 13",
        "lore": "kendall is so into stephs juicy booty"
    },
    {
        "user": "<@291788732544057355>",
        "user_tag": "fz",
        "timestamp": "2023 Oct, 13",
        "lore": "stephanie wishes kendalls butt was bigger"
    }
]